migrations/__init__.py
migrations/api_config.py
migrations/common.py
migrations/daily_snapshot.py
migrations/history.py
migrations/yield_curve.py
migrations_ml-2.1.1.dist-info/METADATA
migrations_ml-2.1.1.dist-info/WHEEL
migrations_ml-2.1.1.dist-info/top_level.txt
migrations_ml-2.1.1.dist-info/RECORD
